ai/__init__.py
ai/batch_norm.py
ai/convolutional.py
ai/graph.py
ai/linear.py
ai/loss.py
ai/module.py
ai/optimizer.py
ai/parameter.py
ai/pooling.py
ai/regularization.py
ai/sequence_models.py
ai/utils.py
import_ai-1.3.16.dist-info/LICENSE
import_ai-1.3.16.dist-info/METADATA
import_ai-1.3.16.dist-info/WHEEL
import_ai-1.3.16.dist-info/top_level.txt
import_ai-1.3.16.dist-info/RECORD
