Metadata-Version: 2.1
Name: import-ai
Version: 1.3.16
Summary: AI library in python using numpy, with end-to-end reverse auto-differentiable dynamic Computational Graph
Home-page: https://github.com/srirambandi/ai
Author: Sri Ram Bandi
Author-email: srirambandi.654@gmail.com
License: UNKNOWN
Platform: UNKNOWN
Classifier: Programming Language :: Python :: 3
Classifier: License :: OSI Approved :: MIT License
Classifier: Operating System :: OS Independent
Requires-Python: >=3.6
Requires-Dist: numpy (>=1.18.1)
Requires-Dist: graphviz (>=0.14)
